rest_auth_multitoken/__init__.py
rest_auth_multitoken/admin.py
rest_auth_multitoken/apps.py
rest_auth_multitoken/migrations/0001_initial.py
rest_auth_multitoken/migrations/__init__.py
rest_auth_multitoken/models.py
rest_auth_multitoken/tests.py
rest_auth_multitoken/utils.py
rest_auth_multitoken/views.py
rest_auth_multitoken-0.2.2.dist-info/WHEEL
rest_auth_multitoken-0.2.2.dist-info/METADATA
rest_auth_multitoken-0.2.2.dist-info/RECORD
