Metadata-Version: 2.1
Name: rest-auth-multitoken
Version: 0.2.2
Summary: Add multiple tokens support to django-rest-auth.
Home-page: https://github.com/makerGeek/rest-auth-multitoken
License: MIT
Author: makerGeek
Author-email: moetez.93@gmail.com
Requires-Python: >=3.9,<4.0
Classifier: License :: OSI Approved :: MIT License
Classifier: Programming Language :: Python :: 3
Classifier: Programming Language :: Python :: 3.9
Requires-Dist: django-rest-auth (>=0.9.5,<0.10.0)
Project-URL: Repository, https://github.com/makerGeek/rest-auth-multitoken
